date_ranges/__init__.py
date_ranges/date_ranges.py
date_ranges/date_utils.py
date_ranges/py.typed
date_ranges-0.1.1.dist-info/licenses/LICENSE
date_ranges-0.1.1.dist-info/METADATA
date_ranges-0.1.1.dist-info/WHEEL
date_ranges-0.1.1.dist-info/top_level.txt
date_ranges-0.1.1.dist-info/RECORD
