Metadata-Version: 2.4
Name: date-ranges
Version: 0.1.1
Summary: A DateRange type and related utility functions
Author-email: Scott Karlin <pypi@karlin-online.com>
License-Expression: MIT
Project-URL: Home Page, https://gitlab.com/sck/date-ranges
Classifier: Programming Language :: Python :: 3
Classifier: Programming Language :: Python :: 3.11
Classifier: Programming Language :: Python :: 3.12
Classifier: Development Status :: 5 - Production/Stable
Classifier: Intended Audience :: Developers
Requires-Python: >=3.11
License-File: LICENSE
Requires-Dist: attrs>=23.1
Provides-Extra: tests
Requires-Dist: pytest>=8.4.1; extra == "tests"
Provides-Extra: build
Requires-Dist: build; extra == "build"
Requires-Dist: twine; extra == "build"
Requires-Dist: packaging; extra == "build"
Provides-Extra: ci
Requires-Dist: pytest>=8.4.1; extra == "ci"
Requires-Dist: twine; extra == "ci"
Requires-Dist: packaging; extra == "ci"
Requires-Dist: ruff; extra == "ci"
Provides-Extra: dev
Requires-Dist: build; extra == "dev"
Requires-Dist: twine; extra == "dev"
Requires-Dist: mypy>=1.16.1; extra == "dev"
Requires-Dist: packaging; extra == "dev"
Requires-Dist: pre-commit>=4.2.0; extra == "dev"
Requires-Dist: pytest>=8.4.1; extra == "dev"
Requires-Dist: pytest-cov>=4.1; extra == "dev"
Requires-Dist: coverage>=7.3; extra == "dev"
Requires-Dist: ruff; extra == "dev"
Dynamic: license-file
